mamba_runner/runner.py
mamba_runner/django_runner.py
mamba_runner/__init__.py
mamba_runner/result.py
mamba_runner-0.0.2.dist-info/WHEEL
mamba_runner-0.0.2.dist-info/RECORD
mamba_runner-0.0.2.dist-info/metadata.json
mamba_runner-0.0.2.dist-info/top_level.txt
mamba_runner-0.0.2.dist-info/DESCRIPTION.rst
mamba_runner-0.0.2.dist-info/METADATA
