Metadata-Version: 2.0
Name: mamba-runner
Version: 0.0.2
Summary: Measure time execution for unittest tests
Home-page: https://github.com/mattack108/mamba-runner
Author: Maciek Lenc
Author-email: matt.lenc@gmail.com
License: MIT
Keywords: unittest timing time mamba tests runner
Platform: UNKNOWN
Classifier: Development Status :: 3 - Alpha
Classifier: Intended Audience :: Developers
Classifier: License :: OSI Approved :: MIT License
Classifier: Programming Language :: Python :: 2
Classifier: Programming Language :: Python :: 2.7
Classifier: Programming Language :: Python :: 3
Classifier: Programming Language :: Python :: 3.3
Classifier: Topic :: Software Development :: Testing
Requires-Dist: blessings
